README.rst
setup.py
pyppm/__init__.py
pyppm/main.py
pyppm.egg-info/PKG-INFO
pyppm.egg-info/SOURCES.txt
pyppm.egg-info/dependency_links.txt
pyppm.egg-info/entry_points.txt
pyppm.egg-info/requires.txt
pyppm.egg-info/top_level.txt