Metadata-Version: 1.0
Name: pyppm
Version: 3.0.2
Summary: python password manager
Home-page: https://github.com/her0e1c1/pwm
Author: Hiroyuki Ishii
Author-email: hiroyuki.ishii.42@gmail.com
License: UNKNOWN
Platform: UNKNOWN
